{
"skeleton": { "hash": "lWK+4kyDs7IlI1X9LkOLEoKrZmw", "spine": "2.1.27", "width": 146.12, "height": 333.03, "images": "./images/" },
"bones": [
	{ "name": "root" },
	{ "name": "bone", "parent": "root", "length": 18.13, "x": 22.27, "y": 92.63, "rotation": 90.9 },
	{ "name": "bone2", "parent": "bone", "x": 142.94, "y": 6.6 },
	{ "name": "bone3", "parent": "bone", "x": 167.57, "y": -3.77, "color": "9c9c9c00" },
	{ "name": "bone4", "parent": "bone", "x": 140.29, "y": -19.99 },
	{ "name": "bone5", "parent": "bone", "x": 188.1, "y": -38.88 },
	{ "name": "bone6", "parent": "bone", "x": 209.18, "y": 6.66 },
	{ "name": "bone7", "parent": "bone", "x": 216.51, "y": -67.09 },
	{ "name": "bone8", "parent": "bone", "x": 165.31, "y": -75.53 }
],
"slots": [
	{ "name": "taideng zuo", "bone": "bone", "attachment": "taideng zuo" },
	{ "name": "taideng zhao", "bone": "bone2", "attachment": "taideng zhao" },
	{ "name": "taideng guang", "bone": "bone3", "attachment": "taideng guang" },
	{ "name": "taideng192", "bone": "bone5", "attachment": "taideng192" },
	{ "name": "taideng192  1", "bone": "bone8", "attachment": "taideng192  1" },
	{ "name": "taideng192  2", "bone": "bone6", "attachment": "taideng192  2" },
	{ "name": "taideng192  3", "bone": "bone7", "attachment": "taideng192  3" },
	{ "name": "taideng192  4", "bone": "bone4", "attachment": "taideng192  4" },
	{ "name": "shanguang2", "bone": "root" },
	{ "name": "shanguang3", "bone": "root" },
	{ "name": "shanguang4", "bone": "root" },
	{ "name": "shanguang5", "bone": "root" },
	{ "name": "shanguang6", "bone": "root" },
	{ "name": "shanguang7", "bone": "root" }
],
"skins": {
	"default": {
		"taideng guang": {
			"taideng guang": { "x": -75.52, "y": -48.42, "rotation": -90.9, "width": 146, "height": 317 }
		},
		"taideng zhao": {
			"taideng zhao": { "x": 26.87, "y": -42.04, "rotation": -90.9, "width": 110, "height": 170 }
		},
		"taideng zuo": {
			"taideng zuo": { "x": 28.6, "y": -16.68, "rotation": -90.9, "width": 77, "height": 213 }
		},
		"taideng192": {
			"taideng192": { "x": 0.14, "y": -1.34, "rotation": -90.9, "width": 9, "height": 9 }
		},
		"taideng192  1": {
			"taideng192  1": { "x": 1.36, "y": 0.13, "rotation": -90.9, "width": 10, "height": 9 }
		},
		"taideng192  2": {
			"taideng192  2": { "x": -0.67, "y": 0.79, "rotation": -90.9, "width": 9, "height": 10 }
		},
		"taideng192  3": {
			"taideng192  3": { "x": -0.68, "y": 0.42, "rotation": -90.9, "width": 9, "height": 9 }
		},
		"taideng192  4": {
			"taideng192  4": { "x": -0.21, "y": 1.03, "rotation": -90.9, "width": 10, "height": 10 }
		}
	}
},
"animations": {
	"animation": {
		"slots": {
			"taideng192": {
				"color": [
					{ "time": 0, "color": "ffffff00", "curve": "stepped" },
					{ "time": 0.3333, "color": "ffffff00" },
					{ "time": 0.4666, "color": "ffffffff", "curve": "stepped" },
					{ "time": 0.5333, "color": "ffffffff" },
					{ "time": 0.6666, "color": "ffffff00", "curve": "stepped" },
					{ "time": 1, "color": "ffffff00" },
					{ "time": 1.1333, "color": "ffffffff", "curve": "stepped" },
					{ "time": 1.2, "color": "ffffffff" },
					{ "time": 1.3333, "color": "ffffff00", "curve": "stepped" },
					{ "time": 1.6666, "color": "ffffff00" },
					{ "time": 1.8, "color": "ffffffff", "curve": "stepped" },
					{ "time": 1.8666, "color": "ffffffff" },
					{ "time": 2.1666, "color": "ffffff00" },
					{ "time": 2.3333, "color": "ffffffff", "curve": "stepped" },
					{ "time": 3.6666, "color": "ffffffff" },
					{ "time": 4, "color": "ffffff00" }
				]
			},
			"taideng guang": {
				"color": [
					{ "time": 0, "color": "ffffff00", "curve": "stepped" },
					{ "time": 2.1666, "color": "ffffff00" },
					{ "time": 2.3333, "color": "ffffffff", "curve": "stepped" },
					{ "time": 3.6666, "color": "ffffffff" },
					{ "time": 4, "color": "ffffff00" }
				]
			},
			"taideng192  1": {
				"color": [
					{ "time": 0, "color": "ffffff00" },
					{ "time": 0.1333, "color": "ffffffff", "curve": "stepped" },
					{ "time": 0.2, "color": "ffffffff" },
					{ "time": 0.3333, "color": "ffffff00", "curve": "stepped" },
					{ "time": 0.6666, "color": "ffffff00" },
					{ "time": 0.8, "color": "ffffffff", "curve": "stepped" },
					{ "time": 0.8666, "color": "ffffffff" },
					{ "time": 1, "color": "ffffff00", "curve": "stepped" },
					{ "time": 1.3333, "color": "ffffff00" },
					{ "time": 1.4666, "color": "ffffffff", "curve": "stepped" },
					{ "time": 1.5333, "color": "ffffffff" },
					{ "time": 1.6666, "color": "ffffff00", "curve": "stepped" },
					{ "time": 2.1666, "color": "ffffff00" },
					{ "time": 2.3333, "color": "ffffffff", "curve": "stepped" },
					{ "time": 3.6666, "color": "ffffffff" },
					{ "time": 4, "color": "ffffff00" }
				]
			},
			"taideng192  2": {
				"color": [
					{ "time": 0, "color": "ffffff00" },
					{ "time": 0.1333, "color": "ffffffff", "curve": "stepped" },
					{ "time": 0.2, "color": "ffffffff" },
					{ "time": 0.3333, "color": "ffffff00", "curve": "stepped" },
					{ "time": 0.6666, "color": "ffffff00" },
					{ "time": 0.8, "color": "ffffffff", "curve": "stepped" },
					{ "time": 0.8666, "color": "ffffffff" },
					{ "time": 1, "color": "ffffff00", "curve": "stepped" },
					{ "time": 1.3333, "color": "ffffff00" },
					{ "time": 1.4666, "color": "ffffffff", "curve": "stepped" },
					{ "time": 1.5333, "color": "ffffffff" },
					{ "time": 1.6666, "color": "ffffff00", "curve": "stepped" },
					{ "time": 2.1666, "color": "ffffff00" },
					{ "time": 2.3333, "color": "ffffffff", "curve": "stepped" },
					{ "time": 3.6666, "color": "ffffffff" },
					{ "time": 4, "color": "ffffff00" }
				]
			},
			"taideng192  3": {
				"color": [
					{ "time": 0, "color": "ffffff00" },
					{ "time": 0.1333, "color": "ffffffff", "curve": "stepped" },
					{ "time": 0.2, "color": "ffffffff" },
					{ "time": 0.3333, "color": "ffffff00", "curve": "stepped" },
					{ "time": 0.6666, "color": "ffffff00" },
					{ "time": 0.8, "color": "ffffffff", "curve": "stepped" },
					{ "time": 0.8666, "color": "ffffffff" },
					{ "time": 1, "color": "ffffff00", "curve": "stepped" },
					{ "time": 1.3333, "color": "ffffff00" },
					{ "time": 1.4666, "color": "ffffffff", "curve": "stepped" },
					{ "time": 1.5333, "color": "ffffffff" },
					{ "time": 1.6666, "color": "ffffff00", "curve": "stepped" },
					{ "time": 2.1666, "color": "ffffff00" },
					{ "time": 2.3333, "color": "ffffffff", "curve": "stepped" },
					{ "time": 3.6666, "color": "ffffffff" },
					{ "time": 4, "color": "ffffff00" }
				]
			},
			"taideng192  4": {
				"color": [
					{ "time": 0, "color": "ffffff00" },
					{ "time": 0.1333, "color": "ffffffff", "curve": "stepped" },
					{ "time": 0.2, "color": "ffffffff" },
					{ "time": 0.3333, "color": "ffffff00", "curve": "stepped" },
					{ "time": 0.6666, "color": "ffffff00" },
					{ "time": 0.8, "color": "ffffffff", "curve": "stepped" },
					{ "time": 0.8666, "color": "ffffffff" },
					{ "time": 1, "color": "ffffff00", "curve": "stepped" },
					{ "time": 1.3333, "color": "ffffff00" },
					{ "time": 1.4666, "color": "ffffffff", "curve": "stepped" },
					{ "time": 1.5333, "color": "ffffffff" },
					{ "time": 1.6666, "color": "ffffff00", "curve": "stepped" },
					{ "time": 2.1666, "color": "ffffff00" },
					{ "time": 2.3333, "color": "ffffffff", "curve": "stepped" },
					{ "time": 3.6666, "color": "ffffffff" },
					{ "time": 4, "color": "ffffff00" }
				]
			}
		},
		"bones": {
			"bone": {
				"rotate": [
					{ "time": 0, "angle": 0 }
				],
				"translate": [
					{ "time": 0, "x": 0, "y": 0 }
				]
			},
			"bone2": {
				"rotate": [
					{ "time": 0, "angle": 0 }
				],
				"translate": [
					{ "time": 0, "x": 0, "y": 0 }
				]
			},
			"bone3": {
				"rotate": [
					{ "time": 0, "angle": 0, "curve": "stepped" },
					{ "time": 2.3333, "angle": 0 }
				],
				"translate": [
					{ "time": 0, "x": 0, "y": 0, "curve": "stepped" },
					{ "time": 2.3333, "x": 0, "y": 0 }
				]
			},
			"bone4": {
				"rotate": [
					{ "time": 0, "angle": 0, "curve": "stepped" },
					{ "time": 0.6666, "angle": 0, "curve": "stepped" },
					{ "time": 1.3333, "angle": 0, "curve": "stepped" },
					{ "time": 2.1666, "angle": 0 }
				],
				"translate": [
					{ "time": 0, "x": 0, "y": 0, "curve": "stepped" },
					{ "time": 0.6666, "x": 0, "y": 0, "curve": "stepped" },
					{ "time": 1.3333, "x": 0, "y": 0, "curve": "stepped" },
					{ "time": 2.1666, "x": 0, "y": 0 }
				],
				"scale": [
					{ "time": 0, "x": 1, "y": 1 },
					{ "time": 0.1333, "x": 1.496, "y": 1.496, "curve": "stepped" },
					{ "time": 0.2, "x": 1.496, "y": 1.496 },
					{ "time": 0.3333, "x": 1, "y": 1, "curve": "stepped" },
					{ "time": 0.6666, "x": 1, "y": 1 },
					{ "time": 0.8, "x": 1.496, "y": 1.496, "curve": "stepped" },
					{ "time": 0.8666, "x": 1.496, "y": 1.496 },
					{ "time": 1, "x": 1, "y": 1, "curve": "stepped" },
					{ "time": 1.3333, "x": 1, "y": 1 },
					{ "time": 1.4666, "x": 1.496, "y": 1.496, "curve": "stepped" },
					{ "time": 1.5333, "x": 1.496, "y": 1.496 },
					{ "time": 1.6666, "x": 1, "y": 1, "curve": "stepped" },
					{ "time": 2.1666, "x": 1, "y": 1 },
					{ "time": 2.3333, "x": 1.496, "y": 1.496 }
				]
			},
			"bone5": {
				"rotate": [
					{ "time": 0, "angle": 0 }
				],
				"translate": [
					{ "time": 0, "x": 0, "y": 0 }
				],
				"scale": [
					{ "time": 0.3333, "x": 1, "y": 1 },
					{ "time": 0.4666, "x": 2.157, "y": 2.157, "curve": "stepped" },
					{ "time": 0.5333, "x": 2.157, "y": 2.157 },
					{ "time": 0.6666, "x": 1, "y": 1, "curve": "stepped" },
					{ "time": 1, "x": 1, "y": 1 },
					{ "time": 1.1333, "x": 2.157, "y": 2.157, "curve": "stepped" },
					{ "time": 1.2, "x": 2.157, "y": 2.157 },
					{ "time": 1.3333, "x": 1, "y": 1, "curve": "stepped" },
					{ "time": 1.6666, "x": 1, "y": 1 },
					{ "time": 1.8, "x": 2.157, "y": 2.157, "curve": "stepped" },
					{ "time": 1.8666, "x": 2.157, "y": 2.157 },
					{ "time": 2.1666, "x": 1, "y": 1 },
					{ "time": 2.3333, "x": 2.157, "y": 2.157 }
				]
			},
			"bone6": {
				"rotate": [
					{ "time": 0, "angle": 0, "curve": "stepped" },
					{ "time": 0.3333, "angle": 0, "curve": "stepped" },
					{ "time": 0.6666, "angle": 0, "curve": "stepped" },
					{ "time": 1, "angle": 0, "curve": "stepped" },
					{ "time": 1.3333, "angle": 0, "curve": "stepped" },
					{ "time": 1.6666, "angle": 0 },
					{ "time": 2.1666, "angle": 0.36 }
				],
				"translate": [
					{ "time": 0, "x": 0, "y": 0, "curve": "stepped" },
					{ "time": 0.3333, "x": 0, "y": 0, "curve": "stepped" },
					{ "time": 0.6666, "x": 0, "y": 0, "curve": "stepped" },
					{ "time": 1, "x": 0, "y": 0, "curve": "stepped" },
					{ "time": 1.3333, "x": 0, "y": 0, "curve": "stepped" },
					{ "time": 1.6666, "x": 0, "y": 0, "curve": "stepped" },
					{ "time": 2.1666, "x": 0, "y": 0 }
				],
				"scale": [
					{ "time": 0, "x": 1, "y": 1 },
					{ "time": 0.1333, "x": 1.444, "y": 1.444, "curve": "stepped" },
					{ "time": 0.2, "x": 1.444, "y": 1.444 },
					{ "time": 0.3333, "x": 1, "y": 1, "curve": "stepped" },
					{ "time": 0.6666, "x": 1, "y": 1 },
					{ "time": 0.8, "x": 1.444, "y": 1.444, "curve": "stepped" },
					{ "time": 0.8666, "x": 1.444, "y": 1.444 },
					{ "time": 1, "x": 1, "y": 1, "curve": "stepped" },
					{ "time": 1.3333, "x": 1, "y": 1 },
					{ "time": 1.4666, "x": 1.444, "y": 1.444, "curve": "stepped" },
					{ "time": 1.5333, "x": 1.444, "y": 1.444 },
					{ "time": 1.6666, "x": 1, "y": 1, "curve": "stepped" },
					{ "time": 2.1666, "x": 1, "y": 1 },
					{ "time": 2.3333, "x": 1.444, "y": 1.444 }
				]
			},
			"bone7": {
				"rotate": [
					{ "time": 0, "angle": 0, "curve": "stepped" },
					{ "time": 0.6666, "angle": 0, "curve": "stepped" },
					{ "time": 1.3333, "angle": 0, "curve": "stepped" },
					{ "time": 2.1666, "angle": 0 }
				],
				"translate": [
					{ "time": 0, "x": 0, "y": 0, "curve": "stepped" },
					{ "time": 0.6666, "x": 0, "y": 0, "curve": "stepped" },
					{ "time": 1.3333, "x": 0, "y": 0, "curve": "stepped" },
					{ "time": 2.1666, "x": 0, "y": 0 }
				],
				"scale": [
					{ "time": 0, "x": 1, "y": 1 },
					{ "time": 0.1333, "x": 1.365, "y": 1.365, "curve": "stepped" },
					{ "time": 0.2, "x": 1.365, "y": 1.365 },
					{ "time": 0.3333, "x": 1, "y": 1, "curve": "stepped" },
					{ "time": 0.6666, "x": 1, "y": 1 },
					{ "time": 0.8, "x": 1.365, "y": 1.365, "curve": "stepped" },
					{ "time": 0.8666, "x": 1.365, "y": 1.365 },
					{ "time": 1, "x": 1, "y": 1, "curve": "stepped" },
					{ "time": 1.3333, "x": 1, "y": 1 },
					{ "time": 1.4666, "x": 1.365, "y": 1.365, "curve": "stepped" },
					{ "time": 1.5333, "x": 1.365, "y": 1.365 },
					{ "time": 1.6666, "x": 1, "y": 1, "curve": "stepped" },
					{ "time": 2.1666, "x": 1, "y": 1 },
					{ "time": 2.3333, "x": 1.365, "y": 1.365 }
				]
			},
			"bone8": {
				"rotate": [
					{ "time": 0, "angle": 0, "curve": "stepped" },
					{ "time": 0.1333, "angle": 0, "curve": "stepped" },
					{ "time": 0.2, "angle": 0, "curve": "stepped" },
					{ "time": 0.3333, "angle": 0, "curve": "stepped" },
					{ "time": 0.6666, "angle": 0, "curve": "stepped" },
					{ "time": 0.8, "angle": 0, "curve": "stepped" },
					{ "time": 0.8666, "angle": 0, "curve": "stepped" },
					{ "time": 1, "angle": 0, "curve": "stepped" },
					{ "time": 1.3333, "angle": 0, "curve": "stepped" },
					{ "time": 1.4666, "angle": 0, "curve": "stepped" },
					{ "time": 1.5333, "angle": 0, "curve": "stepped" },
					{ "time": 1.6666, "angle": 0, "curve": "stepped" },
					{ "time": 2.1666, "angle": 0, "curve": "stepped" },
					{ "time": 2.3333, "angle": 0 }
				],
				"translate": [
					{ "time": 0, "x": 0, "y": 0, "curve": "stepped" },
					{ "time": 0.1333, "x": 0, "y": 0, "curve": "stepped" },
					{ "time": 0.2, "x": 0, "y": 0, "curve": "stepped" },
					{ "time": 0.3333, "x": 0, "y": 0, "curve": "stepped" },
					{ "time": 0.6666, "x": 0, "y": 0, "curve": "stepped" },
					{ "time": 0.8, "x": 0, "y": 0, "curve": "stepped" },
					{ "time": 0.8666, "x": 0, "y": 0, "curve": "stepped" },
					{ "time": 1, "x": 0, "y": 0, "curve": "stepped" },
					{ "time": 1.3333, "x": 0, "y": 0, "curve": "stepped" },
					{ "time": 1.4666, "x": 0, "y": 0, "curve": "stepped" },
					{ "time": 1.5333, "x": 0, "y": 0, "curve": "stepped" },
					{ "time": 1.6666, "x": 0, "y": 0, "curve": "stepped" },
					{ "time": 2.1666, "x": 0, "y": 0, "curve": "stepped" },
					{ "time": 2.3333, "x": 0, "y": 0 }
				],
				"scale": [
					{ "time": 0, "x": 1, "y": 1 },
					{ "time": 0.1333, "x": 1.478, "y": 1.478, "curve": "stepped" },
					{ "time": 0.2, "x": 1.478, "y": 1.478 },
					{ "time": 0.3333, "x": 1, "y": 1, "curve": "stepped" },
					{ "time": 0.6666, "x": 1, "y": 1 },
					{ "time": 0.8, "x": 1.478, "y": 1.478, "curve": "stepped" },
					{ "time": 0.8666, "x": 1.478, "y": 1.478 },
					{ "time": 1, "x": 1, "y": 1, "curve": "stepped" },
					{ "time": 1.3333, "x": 1, "y": 1 },
					{ "time": 1.4666, "x": 1.478, "y": 1.478, "curve": "stepped" },
					{ "time": 1.5333, "x": 1.478, "y": 1.478 },
					{ "time": 1.6666, "x": 1, "y": 1, "curve": "stepped" },
					{ "time": 2.1666, "x": 1, "y": 1 },
					{ "time": 2.3333, "x": 1.478, "y": 1.478 }
				]
			}
		}
	},
	"idle": {
		"slots": {
			"taideng192": {
				"color": [
					{ "time": 0, "color": "ffffff00" }
				]
			},
			"taideng guang": {
				"color": [
					{ "time": 0, "color": "ffffff00" }
				]
			},
			"taideng192  1": {
				"color": [
					{ "time": 0, "color": "ffffff00" }
				]
			},
			"taideng192  2": {
				"color": [
					{ "time": 0, "color": "ffffff00" }
				]
			},
			"taideng192  3": {
				"color": [
					{ "time": 0, "color": "ffffff00" }
				]
			},
			"taideng192  4": {
				"color": [
					{ "time": 0, "color": "ffffff00" }
				]
			}
		},
		"bones": {
			"bone5": {
				"rotate": [
					{ "time": 0, "angle": 0 }
				],
				"translate": [
					{ "time": 0, "x": 0, "y": 0 }
				],
				"scale": [
					{ "time": 0, "x": 1, "y": 1 }
				]
			},
			"bone8": {
				"rotate": [
					{ "time": 0, "angle": 0 }
				],
				"translate": [
					{ "time": 0, "x": 0, "y": 0 }
				],
				"scale": [
					{ "time": 0, "x": 1, "y": 1 }
				]
			},
			"bone6": {
				"rotate": [
					{ "time": 0, "angle": 0 }
				],
				"translate": [
					{ "time": 0, "x": 0, "y": 0 }
				],
				"scale": [
					{ "time": 0, "x": 1, "y": 1 }
				]
			},
			"bone7": {
				"rotate": [
					{ "time": 0, "angle": 0 }
				],
				"translate": [
					{ "time": 0, "x": 0, "y": 0 }
				],
				"scale": [
					{ "time": 0, "x": 1, "y": 1 }
				]
			},
			"bone4": {
				"rotate": [
					{ "time": 0, "angle": 0 }
				],
				"translate": [
					{ "time": 0, "x": 0, "y": 0 }
				],
				"scale": [
					{ "time": 0, "x": 1, "y": 1 }
				]
			},
			"bone3": {
				"rotate": [
					{ "time": 0, "angle": 0 }
				],
				"translate": [
					{ "time": 0, "x": 0, "y": 0 }
				],
				"scale": [
					{ "time": 0, "x": 1, "y": 1 }
				]
			},
			"bone": {
				"rotate": [
					{ "time": 0, "angle": 0 }
				],
				"translate": [
					{ "time": 0, "x": 0, "y": 0 }
				],
				"scale": [
					{ "time": 0, "x": 1, "y": 1 }
				]
			},
			"bone2": {
				"rotate": [
					{ "time": 0, "angle": 0 }
				],
				"translate": [
					{ "time": 0, "x": 0, "y": 0 }
				],
				"scale": [
					{ "time": 0, "x": 1, "y": 1 }
				]
			}
		}
	}
}
}